{
	"parent": "item/handheld",
	"textures": {
		"layer0": "item/wooden_hoe"
	},
	"overrides": [
		{"predicate": {"custom_model_data":0}, "model":"item/wooden_hoe"},

		{"predicate": {"custom_model_data":   1}, "model":"item/weapons/mp5_2d"},
		{"predicate": {"custom_model_data":   2}, "model":"item/weapons/scar_l_2d"},
		{"predicate": {"custom_model_data":   3}, "model":"item/weapons/hkusp_2d"},
		{"predicate": {"custom_model_data":   4}, "model":"item/weapons/ak47_2d"},
		{"predicate": {"custom_model_data":   5}, "model":"item/weapons/deserteagle_2d"},
		{"predicate": {"custom_model_data":   6}, "model":"item/weapons/mp7_2d"},
		{"predicate": {"custom_model_data":   7}, "model":"item/weapons/mosinnagant_2d"},
		{"predicate": {"custom_model_data":   8}, "model":"item/weapons/spas_12_2d"},
		{"predicate": {"custom_model_data":   9}, "model":"item/weapons/fiveseven_2d"},
		{"predicate": {"custom_model_data":   10}, "model":"item/weapons/origin_12_2d"},
		{"predicate": {"custom_model_data":   11}, "model":"item/weapons/fivesevenb_2d"},
		{"predicate": {"custom_model_data":   12}, "model":"item/weapons/famas_2d"},
		{"predicate": {"custom_model_data":   13}, "model":"item/weapons/mcx_virtus_2d"},
		{"predicate": {"custom_model_data":   14}, "model":"item/weapons/kiv23_2d"},
		{"predicate": {"custom_model_data":   15}, "model":"item/weapons/kiv23_custom_2d"},
		{"predicate": {"custom_model_data":   16}, "model":"item/weapons/ktr09_2d"},
		{"predicate": {"custom_model_data":   17}, "model":"item/weapons/ktr09_drum_2d"},
		{"predicate": {"custom_model_data":   18}, "model":"item/weapons/m4a1_2d"},
		{"predicate": {"custom_model_data":   19}, "model":"item/weapons/m4a1_mod2_2d"}
	]
}